stelpar/__init__.py
stelpar/config.py
stelpar/estimate.py
stelpar/metadata.py
stelpar/output.py
stelpar/photometry.py
stelpar/plot.py
stelpar/simulation.py
stelpar/target.py
stelpar/utils.py
stelpar/datafiles/dsep_grid_mag.csv.gz
stelpar/datafiles/dsep_grid_mag_interpolated.csv.gz
stelpar/datafiles/dsep_grid_std.csv.gz
stelpar/datafiles/dsep_grid_std_interpolated.csv.gz
stelpar/datafiles/parsec_grid.csv.gz
stelpar/datafiles/Filter_Profiles/2MASS.H.dat
stelpar/datafiles/Filter_Profiles/2MASS.J.dat
stelpar/datafiles/Filter_Profiles/2MASS.Ks.dat
stelpar/datafiles/Filter_Profiles/GAIA_EDR3.G.dat
stelpar/datafiles/Filter_Profiles/GAIA_EDR3.Gbp.dat
stelpar/datafiles/Filter_Profiles/GAIA_EDR3.Grp.dat
stelpar/datafiles/Filter_Profiles/Generic_Cousins.I.dat
stelpar/datafiles/Filter_Profiles/Generic_Cousins.R.dat
stelpar/datafiles/Filter_Profiles/Generic_Johnson.B.dat
stelpar/datafiles/Filter_Profiles/Generic_Johnson.V.dat
stelpar/datafiles/Filter_Profiles/Hipparcos_Hipparcos.Hp.dat
stelpar/datafiles/Filter_Profiles/PS1.g.dat
stelpar/datafiles/Filter_Profiles/PS1.i.dat
stelpar/datafiles/Filter_Profiles/PS1.r.dat
stelpar/datafiles/Filter_Profiles/PS1.y.dat
stelpar/datafiles/Filter_Profiles/PS1.z.dat
stelpar/datafiles/Filter_Profiles/SDSS.g.dat
stelpar/datafiles/Filter_Profiles/SDSS.i.dat
stelpar/datafiles/Filter_Profiles/SDSS.r.dat
stelpar/datafiles/Filter_Profiles/SDSS.z.dat
stelpar/datafiles/Filter_Profiles/TYCHO_TYCHO.B.dat
stelpar/datafiles/Filter_Profiles/TYCHO_TYCHO.V.dat
stelpar/datafiles/Filter_Profiles/alpha_lyr_stis_010.fits
stelpar-1.0.0.dist-info/licenses/LICENSE
stelpar-1.0.0.dist-info/METADATA
stelpar-1.0.0.dist-info/WHEEL
stelpar-1.0.0.dist-info/top_level.txt
stelpar-1.0.0.dist-info/RECORD
