Metadata-Version: 2.4
Name: stelpar
Version: 1.0.0
Summary: Stellar parameter estimation and analysis tool
Author-email: Matt Fields <fieldsmatthewj@gmail.com>
License-Expression: MIT
Keywords: astronomy,astrophysics,stars,stellar parameters
Classifier: Programming Language :: Python :: 3
Classifier: Operating System :: OS Independent
Requires-Python: >=3.6
License-File: LICENSE
Requires-Dist: numpy
Requires-Dist: numba
Requires-Dist: pandas
Requires-Dist: emcee>=3.0.0
Requires-Dist: astroquery
Requires-Dist: synphot
Requires-Dist: dust_extinction
Requires-Dist: isochrones
Requires-Dist: tqdm
Requires-Dist: matplotlib
Requires-Dist: corner
Requires-Dist: seaborn
Provides-Extra: exe
Requires-Dist: setuptools; extra == "exe"
Provides-Extra: test
Requires-Dist: pytest; extra == "test"
Requires-Dist: pytest-cov; extra == "test"
Provides-Extra: notebook
Requires-Dist: jupyter; extra == "notebook"
Requires-Dist: h5py; extra == "notebook"
Dynamic: license-file
